jupyter_js_tools/__init__.py
jupyter_js_tools/carbon.py
jupyter_js_tools/tic_tac_toe.py
jupyter_js_tools/__pycache__/__init__.cpython-38.pyc
jupyter_js_tools/__pycache__/carbon.cpython-38.pyc
jupyter_js_tools/__pycache__/tic_tac_toe.cpython-38.pyc
jupyter_js_tools/carbon/index.html
jupyter_js_tools/carbon/index.js
jupyter_js_tools/carbon/require.js
jupyter_js_tools/tic_tac_toe/index.html
jupyter_js_tools/tic_tac_toe/index.js
jupyter_js_tools-0.2.0.dist-info/METADATA
jupyter_js_tools-0.2.0.dist-info/WHEEL
jupyter_js_tools-0.2.0.dist-info/top_level.txt
jupyter_js_tools-0.2.0.dist-info/RECORD
