Metadata-Version: 2.1
Name: jupyter-js-tools
Version: 0.2.0
Summary: A small example package
Home-page: https://github.com/lucamattiazzi/jupyter-js-tools
Author: Luca Mattiazzi
Author-email: l.d.mattiazzi@gmail.com
License: UNKNOWN
Platform: UNKNOWN
Classifier: Programming Language :: Python :: 3
Classifier: License :: OSI Approved :: MIT License
Classifier: Operating System :: OS Independent
Requires-Python: >=3.7
